genin2/__init__.py
genin2/cli.py
genin2/compositions.tsv
genin2/dd.xz
genin2/di_discriminator.py
genin2/genin2_core.py
genin2/models.xz
genin2/update_checker.py
genin2/utils.py
genin2-2.1.5.dist-info/licenses/LICENSE
genin2-2.1.5.dist-info/METADATA
genin2-2.1.5.dist-info/WHEEL
genin2-2.1.5.dist-info/entry_points.txt
genin2-2.1.5.dist-info/top_level.txt
genin2-2.1.5.dist-info/RECORD
