Metadata-Version: 2.4
Name: genin2
Version: 2.1.5
Summary: Genin2 is a lightining-fast bioinformatic tool to predict genotypes for H5 viruses belonging to the European clade 2.3.4.4b
Author-email: Alessandro Sartori <asartori@izsvenezie.it>, Edoardo Giussani <egiussani@izsvenezie.it>
Project-URL: Homepage, https://izsvenezie-virology.github.io/genin2
Project-URL: Bug Tracker, https://github.com/izsvenezie-virology/genin2/issues
Keywords: avian-influenza,genotype-inspector,genotype-predictor
Classifier: Programming Language :: Python :: 3
Classifier: Operating System :: OS Independent
Classifier: Environment :: Console
Classifier: Intended Audience :: Science/Research
Classifier: Topic :: Scientific/Engineering :: Bio-Informatics
Requires-Python: >=3.9
License-File: LICENSE
Requires-Dist: biopython>=1.85
Requires-Dist: click>=8.1.0
Requires-Dist: importlib-resources>=6.5.2
Requires-Dist: numpy>=2.0.2
Requires-Dist: joblib>=1.4.0
Requires-Dist: scikit-learn<1.7.0,>=1.6.1
Requires-Dist: requests>=2.32.3
Dynamic: license-file
